LICENSE
MANIFEST.in
README.md
setup.cfg
setup.py
src/ethairballoons/__init__.py
src/ethairballoons/ethairballoons.py
src/ethairballoons/example.py
src/ethairballoons.egg-info/PKG-INFO
src/ethairballoons.egg-info/SOURCES.txt
src/ethairballoons.egg-info/dependency_links.txt
src/ethairballoons.egg-info/requires.txt
src/ethairballoons.egg-info/top_level.txt