Metadata-Version: 2.1
Name: ethairballoons
Version: 1.0.10
Home-page: https://github.com/petrosDemetrakopoulos/ethairballoons.py
Author: Petros Demetrakopoulos
Author-email: petrosdem@gamil.com
License: MIT
Keywords: blockchain ethereum web3 orm data database smart contracts library
License-File: LICENSE
